helloflask/__init__.py
helloflask/__main__.py
helloflask/classes.py
helloflask/cmdline.py
helloflask/constants.json
helloflask/run.py
helloflask/controllers/__init__.py
helloflask/controllers/os_utils.py
helloflask/controllers/packages_utils.py
helloflask/controllers/snippets_utils.py
helloflask/controllers/ui_utils.py
helloflask/controllers/venv_utils.py
helloflask/snippets/__init__.py
helloflask/snippets/app.py
helloflask/snippets/run.py
HelloFlask-1.2.0.dist-info/LICENSE
HelloFlask-1.2.0.dist-info/METADATA
HelloFlask-1.2.0.dist-info/WHEEL
HelloFlask-1.2.0.dist-info/entry_points.txt
HelloFlask-1.2.0.dist-info/top_level.txt
HelloFlask-1.2.0.dist-info/RECORD
