Metadata-Version: 2.1
Name: HelloFlask
Version: 1.2.0
Summary: Boostrap a Flask project with boilerplate and virtual environment.
Home-page: https://github.com/ElMehdi19/HelloFlask
Author: El Mehdi Rami
Author-email: elmehdirami5@gmail.com
License: MIT
Platform: UNKNOWN
Classifier: License :: OSI Approved :: MIT License
Classifier: Programming Language :: Python :: 3
Classifier: Programming Language :: Python :: 3.7
Requires-Python: >=3.6.*
Requires-Dist: colorama
Requires-Dist: tqdm
